ddb_single/__init__.py
ddb_single/_cli.py
ddb_single/error.py
ddb_single/model.py
ddb_single/query.py
ddb_single/table.py
ddb_single/utils_botos.py
ddb_single-0.5.8.dist-info/METADATA
ddb_single-0.5.8.dist-info/WHEEL
ddb_single-0.5.8.dist-info/entry_points.txt
ddb_single-0.5.8.dist-info/RECORD
