Metadata-Version: 2.3
Name: ddb_single
Version: 0.5.8
Summary: Python DynamoDB interface, specialized in single-table design.
License: MIT
Keywords: aws,dynamodb,serverless
Author: medaka0213
Requires-Python: >=3.10,<4.0
Classifier: License :: OSI Approved :: MIT License
Classifier: Programming Language :: Python :: 3
Classifier: Programming Language :: Python :: 3.10
Classifier: Programming Language :: Python :: 3.11
Classifier: Programming Language :: Python :: 3.12
Classifier: Programming Language :: Python :: 3.13
Requires-Dist: boto3 (>=1.34.79,<2.0.0)
Requires-Dist: click (>=8.1,<9.0)
Project-URL: Homepage, https://medaka0213.github.io/DynamoDB-SingleTable/
Project-URL: Repository, https://github.com/medaka0213/DynamoDB-SingleTable
